fancymail/__init__.py
fancymail/emailrelated.py
fancymail/send.py
django_fancymail_verteva-1.0.dist-info/LICENSE
django_fancymail_verteva-1.0.dist-info/METADATA
django_fancymail_verteva-1.0.dist-info/WHEEL
django_fancymail_verteva-1.0.dist-info/top_level.txt
django_fancymail_verteva-1.0.dist-info/RECORD
