Metadata-Version: 2.1
Name: django-fancymail-verteva
Version: 1.0
Summary: Email templating for Django
Home-page: http://github.com/litchfield/django-fancymail
Author: Simon Litchfield
Author-email: simon@s29.com.au
License: MIT License
Platform: any
Classifier: Development Status :: 3 - Alpha
Classifier: Environment :: Web Environment
Classifier: Intended Audience :: Developers
Classifier: License :: OSI Approved :: MIT License
Classifier: Operating System :: OS Independent
Classifier: Programming Language :: Python
Classifier: Framework :: Django
License-File: LICENSE
